watchmen_lineage/__init__.py
watchmen_lineage/index.py
watchmen_lineage/lineage_setting.py
watchmen_lineage/ml/__init__.py
watchmen_lineage/ml/mapping_similar.py
watchmen_lineage/model/__init__.py
watchmen_lineage/model/ast.py
watchmen_lineage/model/lineage.py
watchmen_lineage/router/__init__.py
watchmen_lineage/router/lineage_router.py
watchmen_lineage/service/__init__.py
watchmen_lineage/service/builder/__init__.py
watchmen_lineage/service/builder/graphic_builder.py
watchmen_lineage/service/builder/index.py
watchmen_lineage/service/builder/indicator_lineage.py
watchmen_lineage/service/builder/loader.py
watchmen_lineage/service/builder/objective_lineage.py
watchmen_lineage/service/builder/pipeline_lineage.py
watchmen_lineage/service/builder/subject_lineage.py
watchmen_lineage/service/builder/topic_lineage.py
watchmen_lineage/service/compute_service.py
watchmen_lineage/service/lineage_cache.py
watchmen_lineage/service/lineage_service.py
watchmen_lineage/service/memory/__init__.py
watchmen_lineage/service/memory/memory_compute_service.py
watchmen_lineage/service/table/__init__.py
watchmen_lineage/service/table/table_compute_service.py
watchmen_lineage/storage/__init__.py
watchmen_lineage/storage/lineage_storage.py
watchmen_lineage/utils/__init__.py
watchmen_lineage/utils/constant_utils.py
watchmen_lineage/utils/id_utils.py
watchmen_lineage/utils/size_utils.py
watchmen_lineage/utils/utils.py
watchmen_lineage-18.0.1.dist-info/METADATA
watchmen_lineage-18.0.1.dist-info/WHEEL
watchmen_lineage-18.0.1.dist-info/licenses/LICENSE
watchmen_lineage-18.0.1.dist-info/RECORD
