Metadata-Version: 2.4
Name: watchmen-lineage
Version: 18.0.1
Summary: 
License-File: LICENSE
Author: luke0623
Author-email: luke0623@outlook.com
Requires-Python: >=3.12,<3.13
Classifier: Programming Language :: Python :: 3
Classifier: Programming Language :: Python :: 3.12
Requires-Dist: networkx (>=3.4.2,<4.0.0)
Requires-Dist: watchmen-data-surface (==18.0.1)
Requires-Dist: watchmen-indicator-surface (==18.0.1)
Requires-Dist: watchmen-inquiry-surface (==18.0.1)
Requires-Dist: watchmen-pipeline-surface (==18.0.1)
